<annotation>
	<folder>huashengtupian</folder>
	<filename>1409.jpg</filename>
	<path>D:\huashengtupian\1409.jpg</path>
	<source>
		<database>Unknown</database>
	</source>
	<size>
		<width>1389</width>
		<height>1042</height>
		<depth>3</depth>
	</size>
	<segmented>0</segmented>
	<object>
		<name>h</name>
		<pose>Unspecified</pose>
		<truncated>0</truncated>
		<difficult>0</difficult>
		<bndbox>
			<xmin>707</xmin>
			<ymin>572</ymin>
			<xmax>813</xmax>
			<ymax>661</ymax>
		</bndbox>
	</object>
	<object>
		<name>h</name>
		<pose>Unspecified</pose>
		<truncated>0</truncated>
		<difficult>0</difficult>
		<bndbox>
			<xmin>476</xmin>
			<ymin>362</ymin>
			<xmax>589</xmax>
			<ymax>449</ymax>
		</bndbox>
	</object>
	<object>
		<name>h</name>
		<pose>Unspecified</pose>
		<truncated>0</truncated>
		<difficult>0</difficult>
		<bndbox>
			<xmin>746</xmin>
			<ymin>241</ymin>
			<xmax>887</xmax>
			<ymax>349</ymax>
		</bndbox>
	</object>
	<object>
		<name>h</name>
		<pose>Unspecified</pose>
		<truncated>0</truncated>
		<difficult>0</difficult>
		<bndbox>
			<xmin>360</xmin>
			<ymin>517</ymin>
			<xmax>452</xmax>
			<ymax>573</ymax>
		</bndbox>
	</object>
	<object>
		<name>h</name>
		<pose>Unspecified</pose>
		<truncated>0</truncated>
		<difficult>0</difficult>
		<bndbox>
			<xmin>304</xmin>
			<ymin>696</ymin>
			<xmax>376</xmax>
			<ymax>747</ymax>
		</bndbox>
	</object>
	<object>
		<name>h</name>
		<pose>Unspecified</pose>
		<truncated>0</truncated>
		<difficult>0</difficult>
		<bndbox>
			<xmin>133</xmin>
			<ymin>559</ymin>
			<xmax>215</xmax>
			<ymax>625</ymax>
		</bndbox>
	</object>
	<object>
		<name>l</name>
		<pose>Unspecified</pose>
		<truncated>0</truncated>
		<difficult>0</difficult>
		<bndbox>
			<xmin>329</xmin>
			<ymin>742</ymin>
			<xmax>465</xmax>
			<ymax>839</ymax>
		</bndbox>
	</object>
	<object>
		<name>l</name>
		<pose>Unspecified</pose>
		<truncated>0</truncated>
		<difficult>0</difficult>
		<bndbox>
			<xmin>398</xmin>
			<ymin>596</ymin>
			<xmax>503</xmax>
			<ymax>718</ymax>
		</bndbox>
	</object>
</annotation>
